agents/__init__.py
agents/base.py
agents/dqn.py
matex-0.1.0.dist-info/LICENSE
matex-0.1.0.dist-info/METADATA
matex-0.1.0.dist-info/WHEEL
matex-0.1.0.dist-info/top_level.txt
matex-0.1.0.dist-info/RECORD
