Metadata-Version: 2.1
Name: matex
Version: 0.1.0
Summary: A collection of reinforcement learning algorithms
Author: ksterx
Requires-Python: >=3.9
License-File: LICENSE
Requires-Dist: torch
Requires-Dist: gymnasium
Requires-Dist: tensorboard
